denmune/__init__.py
denmune/denmune.py
denmune-1.18.5.dist-info/LICENSE
denmune-1.18.5.dist-info/METADATA
denmune-1.18.5.dist-info/WHEEL
denmune-1.18.5.dist-info/top_level.txt
denmune-1.18.5.dist-info/RECORD
